attack_dashboard/__init__.py
attack_dashboard/__main__.py
attack_dashboard/dashboard_data/mitre_dashboards.sh
attack_dashboard/dashboard_data/objects/dashboard/ALL_MITRE_ATTACK__HELK.ndjson
attack_dashboard/dashboard_data/objects/dashboard/MITRE_ATTACK_GROUPS__HELK.ndjson
attack_dashboard/dashboard_data/objects/index-pattern/mitre_attack.ndjson
attack_dashboard/dashboard_data/objects/search/Global_Discover.ndjson
attack_dashboard/dashboard_data/objects/search/IOC_Discover.ndjson
attack_dashboard/dashboard_data/objects/search/mitre_attack_discover.ndjson
attack_dashboard/dashboard_data/objects/visualization/mitre_attack_data_sources_techniques.ndjson
attack_dashboard/dashboard_data/objects/visualization/mitre_attack_group_relationship.ndjson
attack_dashboard/dashboard_data/objects/visualization/mitre_attack_group_select.ndjson
attack_dashboard/dashboard_data/objects/visualization/mitre_attack_groups_matrices.ndjson
attack_dashboard/dashboard_data/objects/visualization/mitre_attack_groups_software_cloud.ndjson
attack_dashboard/dashboard_data/objects/visualization/mitre_attack_groups_tactics.ndjson
attack_dashboard/dashboard_data/objects/visualization/mitre_attack_groups_techniques.ndjson
attack_dashboard/dashboard_data/objects/visualization/mitre_attack_groups_techniques_bar.ndjson
attack_dashboard/dashboard_data/objects/visualization/mitre_attack_mitigation_technique.ndjson
attack_dashboard/dashboard_data/objects/visualization/mitre_attack_permissions_required.ndjson
attack_dashboard/dashboard_data/objects/visualization/mitre_attack_select.ndjson
attack_dashboard/dashboard_data/objects/visualization/mitre_attack_software_groups.ndjson
attack_dashboard/dashboard_data/objects/visualization/mitre_attack_tactic_techniques.ndjson
attack_dashboard/dashboard_data/objects/visualization/mitre_attack_technique_data_sources.ndjson
attack_dashboard/dashboard_data/objects/visualization/mitre_attack_technique_data_sources_cloud.ndjson
attack_dashboard-0.11.11.dist-info/METADATA
attack_dashboard-0.11.11.dist-info/WHEEL
attack_dashboard-0.11.11.dist-info/entry_points.txt
attack_dashboard-0.11.11.dist-info/RECORD
