Metadata-Version: 2.1
Name: attack-dashboard
Version: 0.11.11
Summary: Update ATT&CK data for the HELK kibana dashboard.
Home-page: https://github.com/3lLobo/mitre-dash
License: MIT
Author: 3lLobo
Author-email: flocwolf@gmail.com
Requires-Python: >=3.10,<4.0
Classifier: License :: OSI Approved :: MIT License
Classifier: Programming Language :: Python :: 3
Classifier: Programming Language :: Python :: 3.10
Classifier: Programming Language :: Python :: 3.11
Requires-Dist: addict (>=2.4.0,<3.0.0)
Requires-Dist: mitreattack-python (>=2.0.6,<3.0.0)
Requires-Dist: pandas (>=1.5.3,<2.0.0)
Requires-Dist: stix2 (>=3.0.1,<4.0.0)
Requires-Dist: taxii2-client (>=2.3.0,<3.0.0)
Requires-Dist: tqdm (>=4.65.0,<5.0.0)
Project-URL: Repository, https://github.com/3lLobo/mitre-dash
